{"version":1,"resource":"file:///home/michell/Workspace/multidadosti/infra-multierp/ansible.cfg","entries":[{"id":"BaeT.cfg","timestamp":1695252790640},{"id":"3g4V.cfg","timestamp":1695252830340},{"id":"xw1Q.cfg","timestamp":1695253045733},{"id":"KDr4.cfg","timestamp":1695253056585},{"id":"ABMK.cfg","timestamp":1695253307206},{"id":"tsIS.cfg","source":"undoRedo.source","timestamp":1695253330489},{"id":"ioG8.cfg","timestamp":1695253553591},{"id":"1jWs.cfg","timestamp":1695316491466},{"id":"Tf1D.cfg","timestamp":1695319079943}]}