{"version":1,"content":"{\"storage\":{\"ces/skipSurvey\":{\"version\":1,\"value\":\"1.82.2\"},\"colorThemeData\":{\"version\":1,\"value\":\"{\\\"id\\\":\\\"vs-dark arcticicestudio-nord-visual-studio-code-themes-nord-color-theme-json\\\",\\\"label\\\":\\\"Nord\\\",\\\"settingsId\\\":\\\"Nord\\\",\\\"themeTokenColors\\\":[{\\\"settings\\\":{\\\"foreground\\\":\\\"#d8dee9ff\\\",\\\"background\\\":\\\"#2e3440ff\\\"}},{\\\"settings\\\":{\\\"fontStyle\\\":\\\"italic\\\"},\\\"scope\\\":\\\"emphasis\\\"},{\\\"settings\\\":{\\\"fontStyle\\\":\\\"bold\\\"},\\\"scope\\\":\\\"strong\\\"},{\\\"settings\\\":{\\\"foreground\\\":\\\"#616E88\\\"},\\\"scope\\\":\\\"comment\\\"},{\\\"settings\\\":{\\\"foreground\\\":\\\"#EBCB8B\\\"},\\\"scope\\\":\\\"constant.character\\\"},{\\\"settings\\\":{\\\"foreground\\\":\\\"#EBCB8B\\\"},\\\"scope\\\":\\\"constant.character.escape\\\"},{\\\"settings\\\":{\\\"foreground\\\":\\\"#81A1C1\\\"},\\\"scope\\\":\\\"constant.language\\\"},{\\\"settings\\\":{\\\"foreground\\\":\\\"#B48EAD\\\"},\\\"scope\\\":\\\"constant.numeric\\\"},{\\\"settings\\\":{\\\"foreground\\\":\\\"#EBCB8B\\\"},\\\"scope\\\":\\\"constant.regexp\\\"},{\\\"settings\\\":{\\\"foreground\\\":\\\"#8FBCBB\\\"},\\\"scope\\\":[\\\"entity.name.class\\\",\\\"entity.name.type.class\\\"]},{\\\"settings\\\":{\\\"foreground\\\":\\\"#88C0D0\\\"},\\\"scope\\\":\\\"entity.name.function\\\"},{\\\"settings\\\":{\\\"foreground\\\":\\\"#81A1C1\\\"},\\\"scope\\\":\\\"entity.name.tag\\\"},{\\\"settings\\\":{\\\"foreground\\\":\\\"#8FBCBB\\\"},\\\"scope\\\":\\\"entity.other.attribute-name\\\"},{\\\"settings\\\":{\\\"fontStyle\\\":\\\"bold\\\",\\\"foreground\\\":\\\"#8FBCBB\\\"},\\\"scope\\\":\\\"entity.other.inherited-class\\\"},{\\\"settings\\\":{\\\"foreground\\\":\\\"#D8DEE9\\\",\\\"background\\\":\\\"#EBCB8B\\\"},\\\"scope\\\":\\\"invalid.deprecated\\\"},{\\\"settings\\\":{\\\"foreground\\\":\\\"#D8DEE9\\\",\\\"background\\\":\\\"#BF616A\\\"},\\\"scope\\\":\\\"invalid.illegal\\\"},{\\\"settings\\\":{\\\"foreground\\\":\\\"#81A1C1\\\"},\\\"scope\\\":\\\"keyword\\\"},{\\\"settings\\\":{\\\"foreground\\\":\\\"#81A1C1\\\"},\\\"scope\\\":\\\"keyword.operator\\\"},{\\\"settings\\\":{\\\"foreground\\\":\\\"#81A1C1\\\"},\\\"scope\\\":\\\"keyword.other.new\\\"},{\\\"settings\\\":{\\\"fontStyle\\\":\\\"bold\\\"},\\\"scope\\\":\\\"markup.bold\\\"},{\\\"settings\\\":{\\\"foreground\\\":\\\"#EBCB8B\\\"},\\\"scope\\\":\\\"markup.changed\\\"},{\\\"settings\\\":{\\\"foreground\\\":\\\"#BF616A\\\"},\\\"scope\\\":\\\"markup.deleted\\\"},{\\\"settings\\\":{\\\"foreground\\\":\\\"#A3BE8C\\\"},\\\"scope\\\":\\\"markup.inserted\\\"},{\\\"settings\\\":{\\\"foreground\\\":\\\"#5E81AC\\\"},\\\"scope\\\":\\\"meta.preprocessor\\\"},{\\\"settings\\\":{\\\"foreground\\\":\\\"#ECEFF4\\\"},\\\"scope\\\":\\\"punctuation\\\"},{\\\"settings\\\":{\\\"foreground\\\":\\\"#ECEFF4\\\"},\\\"scope\\\":[\\\"punctuation.definition.method-parameters\\\",\\\"punctuation.definition.function-parameters\\\",\\\"punctuation.definition.parameters\\\"]},{\\\"settings\\\":{\\\"foreground\\\":\\\"#81A1C1\\\"},\\\"scope\\\":\\\"punctuation.definition.tag\\\"},{\\\"settings\\\":{\\\"foreground\\\":\\\"#616E88\\\"},\\\"scope\\\":[\\\"punctuation.definition.comment\\\",\\\"punctuation.end.definition.comment\\\",\\\"punctuation.start.definition.comment\\\"]},{\\\"settings\\\":{\\\"foreground\\\":\\\"#ECEFF4\\\"},\\\"scope\\\":\\\"punctuation.section\\\"},{\\\"settings\\\":{\\\"foreground\\\":\\\"#81A1C1\\\"},\\\"scope\\\":[\\\"punctuation.section.embedded.begin\\\",\\\"punctuation.section.embedded.end\\\"]},{\\\"settings\\\":{\\\"foreground\\\":\\\"#81A1C1\\\"},\\\"scope\\\":\\\"punctuation.terminator\\\"},{\\\"settings\\\":{\\\"foreground\\\":\\\"#81A1C1\\\"},\\\"scope\\\":\\\"punctuation.definition.variable\\\"},{\\\"settings\\\":{\\\"foreground\\\":\\\"#81A1C1\\\"},\\\"scope\\\":\\\"storage\\\"},{\\\"settings\\\":{\\\"foreground\\\":\\\"#A3BE8C\\\"},\\\"scope\\\":\\\"string\\\"},{\\\"settings\\\":{\\\"foreground\\\":\\\"#EBCB8B\\\"},\\\"scope\\\":\\\"string.regexp\\\"},{\\\"settings\\\":{\\\"foreground\\\":\\\"#8FBCBB\\\"},\\\"scope\\\":\\\"support.class\\\"},{\\\"settings\\\":{\\\"foreground\\\":\\\"#81A1C1\\\"},\\\"scope\\\":\\\"support.constant\\\"},{\\\"settings\\\":{\\\"foreground\\\":\\\"#88C0D0\\\"},\\\"scope\\\":\\\"support.function\\\"},{\\\"settings\\\":{\\\"foreground\\\":\\\"#81A1C1\\\"},\\\"scope\\\":\\\"support.function.construct\\\"},{\\\"settings\\\":{\\\"foreground\\\":\\\"#8FBCBB\\\"},\\\"scope\\\":\\\"support.type\\\"},{\\\"settings\\\":{\\\"foreground\\\":\\\"#8FBCBB\\\"},\\\"scope\\\":\\\"support.type.exception\\\"},{\\\"settings\\\":{\\\"foreground\\\":\\\"#b48ead\\\"},\\\"scope\\\":\\\"token.debug-token\\\"},{\\\"settings\\\":{\\\"foreground\\\":\\\"#bf616a\\\"},\\\"scope\\\":\\\"token.error-token\\\"},{\\\"settings\\\":{\\\"foreground\\\":\\\"#88c0d0\\\"},\\\"scope\\\":\\\"token.info-token\\\"},{\\\"settings\\\":{\\\"foreground\\\":\\\"#ebcb8b\\\"},\\\"scope\\\":\\\"token.warn-token\\\"},{\\\"settings\\\":{\\\"foreground\\\":\\\"#D8DEE9\\\"},\\\"scope\\\":\\\"variable.other\\\"},{\\\"settings\\\":{\\\"foreground\\\":\\\"#81A1C1\\\"},\\\"scope\\\":\\\"variable.language\\\"},{\\\"settings\\\":{\\\"foreground\\\":\\\"#D8DEE9\\\"},\\\"scope\\\":\\\"variable.parameter\\\"},{\\\"settings\\\":{\\\"foreground\\\":\\\"#81A1C1\\\"},\\\"scope\\\":\\\"punctuation.separator.pointer-access.c\\\"},{\\\"settings\\\":{\\\"foreground\\\":\\\"#8FBCBB\\\"},\\\"scope\\\":[\\\"source.c meta.preprocessor.include\\\",\\\"source.c string.quoted.other.lt-gt.include\\\"]},{\\\"settings\\\":{\\\"foreground\\\":\\\"#5E81AC\\\",\\\"fontStyle\\\":\\\"bold\\\"},\\\"scope\\\":[\\\"source.cpp keyword.control.directive.conditional\\\",\\\"source.cpp punctuation.definition.directive\\\",\\\"source.c keyword.control.directive.conditional\\\",\\\"source.c punctuation.definition.directive\\\"]},{\\\"settings\\\":{\\\"foreground\\\":\\\"#B48EAD\\\"},\\\"scope\\\":\\\"source.css constant.other.color.rgb-value\\\"},{\\\"settings\\\":{\\\"foreground\\\":\\\"#88C0D0\\\"},\\\"scope\\\":\\\"source.css meta.property-value\\\"},{\\\"settings\\\":{\\\"foreground\\\":\\\"#D08770\\\"},\\\"scope\\\":[\\\"source.css keyword.control.at-rule.media\\\",\\\"source.css keyword.control.at-rule.media punctuation.definition.keyword\\\"]},{\\\"settings\\\":{\\\"foreground\\\":\\\"#81A1C1\\\"},\\\"scope\\\":\\\"source.css punctuation.definition.keyword\\\"},{\\\"settings\\\":{\\\"foreground\\\":\\\"#D8DEE9\\\"},\\\"scope\\\":\\\"source.css support.type.property-name\\\"},{\\\"settings\\\":{\\\"foreground\\\":\\\"#8FBCBB\\\"},\\\"scope\\\":\\\"source.diff meta.diff.range.context\\\"},{\\\"settings\\\":{\\\"foreground\\\":\\\"#8FBCBB\\\"},\\\"scope\\\":\\\"source.diff meta.diff.header.from-file\\\"},{\\\"settings\\\":{\\\"foreground\\\":\\\"#8FBCBB\\\"},\\\"scope\\\":\\\"source.diff punctuation.definition.from-file\\\"},{\\\"settings\\\":{\\\"foreground\\\":\\\"#8FBCBB\\\"},\\\"scope\\\":\\\"source.diff punctuation.definition.range\\\"},{\\\"settings\\\":{\\\"foreground\\\":\\\"#81A1C1\\\"},\\\"scope\\\":\\\"source.diff punctuation.definition.separator\\\"},{\\\"settings\\\":{\\\"foreground\\\":\\\"#8FBCBB\\\"},\\\"scope\\\":\\\"entity.name.type.module.elixir\\\"},{\\\"settings\\\":{\\\"foreground\\\":\\\"#D8DEE9\\\",\\\"fontStyle\\\":\\\"bold\\\"},\\\"scope\\\":\\\"variable.other.readwrite.module.elixir\\\"},{\\\"settings\\\":{\\\"foreground\\\":\\\"#D8DEE9\\\",\\\"fontStyle\\\":\\\"bold\\\"},\\\"scope\\\":\\\"constant.other.symbol.elixir\\\"},{\\\"settings\\\":{\\\"foreground\\\":\\\"#8FBCBB\\\"},\\\"scope\\\":\\\"variable.other.constant.elixir\\\"},{\\\"settings\\\":{\\\"foreground\\\":\\\"#EBCB8B\\\"},\\\"scope\\\":\\\"source.go constant.other.placeholder.go\\\"},{\\\"settings\\\":{\\\"foreground\\\":\\\"#81A1C1\\\"},\\\"scope\\\":\\\"source.java comment.block.documentation.javadoc punctuation.definition.entity.html\\\"},{\\\"settings\\\":{\\\"foreground\\\":\\\"#D8DEE9\\\"},\\\"scope\\\":\\\"source.java constant.other\\\"},{\\\"settings\\\":{\\\"foreground\\\":\\\"#8FBCBB\\\"},\\\"scope\\\":\\\"source.java keyword.other.documentation\\\"},{\\\"settings\\\":{\\\"foreground\\\":\\\"#8FBCBB\\\"},\\\"scope\\\":\\\"source.java keyword.other.documentation.author.javadoc\\\"},{\\\"settings\\\":{\\\"foreground\\\":\\\"#8FBCBB\\\"},\\\"scope\\\":[\\\"source.java keyword.other.documentation.directive\\\",\\\"source.java keyword.other.documentation.custom\\\"]},{\\\"settings\\\":{\\\"foreground\\\":\\\"#8FBCBB\\\"},\\\"scope\\\":\\\"source.java keyword.other.documentation.see.javadoc\\\"},{\\\"settings\\\":{\\\"foreground\\\":\\\"#88C0D0\\\"},\\\"scope\\\":\\\"source.java meta.method-call meta.method\\\"},{\\\"settings\\\":{\\\"foreground\\\":\\\"#8FBCBB\\\"},\\\"scope\\\":[\\\"source.java meta.tag.template.link.javadoc\\\",\\\"source.java string.other.link.title.javadoc\\\"]},{\\\"settings\\\":{\\\"foreground\\\":\\\"#88C0D0\\\"},\\\"scope\\\":\\\"source.java meta.tag.template.value.javadoc\\\"},{\\\"settings\\\":{\\\"foreground\\\":\\\"#8FBCBB\\\"},\\\"scope\\\":\\\"source.java punctuation.definition.keyword.javadoc\\\"},{\\\"settings\\\":{\\\"foreground\\\":\\\"#616E88\\\"},\\\"scope\\\":[\\\"source.java punctuation.definition.tag.begin.javadoc\\\",\\\"source.java punctuation.definition.tag.end.javadoc\\\"]},{\\\"settings\\\":{\\\"foreground\\\":\\\"#8FBCBB\\\"},\\\"scope\\\":\\\"source.java storage.modifier.import\\\"},{\\\"settings\\\":{\\\"foreground\\\":\\\"#8FBCBB\\\"},\\\"scope\\\":\\\"source.java storage.modifier.package\\\"},{\\\"settings\\\":{\\\"foreground\\\":\\\"#8FBCBB\\\"},\\\"scope\\\":\\\"source.java storage.type\\\"},{\\\"settings\\\":{\\\"foreground\\\":\\\"#D08770\\\"},\\\"scope\\\":\\\"source.java storage.type.annotation\\\"},{\\\"settings\\\":{\\\"foreground\\\":\\\"#8FBCBB\\\"},\\\"scope\\\":\\\"source.java storage.type.generic\\\"},{\\\"settings\\\":{\\\"foreground\\\":\\\"#81A1C1\\\"},\\\"scope\\\":\\\"source.java storage.type.primitive\\\"},{\\\"settings\\\":{\\\"foreground\\\":\\\"#D08770\\\"},\\\"scope\\\":[\\\"source.js punctuation.decorator\\\",\\\"source.js meta.decorator variable.other.readwrite\\\",\\\"source.js meta.decorator entity.name.function\\\"]},{\\\"settings\\\":{\\\"foreground\\\":\\\"#88C0D0\\\"},\\\"scope\\\":\\\"source.js meta.object-literal.key\\\"},{\\\"settings\\\":{\\\"foreground\\\":\\\"#8FBCBB\\\"},\\\"scope\\\":\\\"source.js storage.type.class.jsdoc\\\"},{\\\"settings\\\":{\\\"foreground\\\":\\\"#81A1C1\\\"},\\\"scope\\\":[\\\"source.js string.quoted.template punctuation.quasi.element.begin\\\",\\\"source.js string.quoted.template punctuation.quasi.element.end\\\",\\\"source.js string.template punctuation.definition.template-expression\\\"]},{\\\"settings\\\":{\\\"foreground\\\":\\\"#ECEFF4\\\"},\\\"scope\\\":\\\"source.js string.quoted.template meta.method-call.with-arguments\\\"},{\\\"settings\\\":{\\\"foreground\\\":\\\"#D8DEE9\\\"},\\\"scope\\\":[\\\"source.js string.template meta.template.expression support.variable.property\\\",\\\"source.js string.template meta.template.expression variable.other.object\\\"]},{\\\"settings\\\":{\\\"foreground\\\":\\\"#81A1C1\\\"},\\\"scope\\\":\\\"source.js support.type.primitive\\\"},{\\\"settings\\\":{\\\"foreground\\\":\\\"#D8DEE9\\\"},\\\"scope\\\":\\\"source.js variable.other.object\\\"},{\\\"settings\\\":{\\\"foreground\\\":\\\"#8FBCBB\\\"},\\\"scope\\\":\\\"source.js variable.other.readwrite.alias\\\"},{\\\"settings\\\":{\\\"foreground\\\":\\\"#ECEFF4\\\"},\\\"scope\\\":[\\\"source.js meta.embedded.line meta.brace.square\\\",\\\"source.js meta.embedded.line meta.brace.round\\\",\\\"source.js string.quoted.template meta.brace.square\\\",\\\"source.js string.quoted.template meta.brace.round\\\"]},{\\\"settings\\\":{\\\"foreground\\\":\\\"#EBCB8B\\\"},\\\"scope\\\":\\\"text.html.basic constant.character.entity.html\\\"},{\\\"settings\\\":{\\\"foreground\\\":\\\"#D08770\\\",\\\"fontStyle\\\":\\\"italic\\\"},\\\"scope\\\":\\\"text.html.basic constant.other.inline-data\\\"},{\\\"settings\\\":{\\\"foreground\\\":\\\"#5E81AC\\\"},\\\"scope\\\":\\\"text.html.basic meta.tag.sgml.doctype\\\"},{\\\"settings\\\":{\\\"foreground\\\":\\\"#81A1C1\\\"},\\\"scope\\\":\\\"text.html.basic punctuation.definition.entity\\\"},{\\\"settings\\\":{\\\"foreground\\\":\\\"#88C0D0\\\"},\\\"scope\\\":\\\"source.properties entity.name.section.group-title.ini\\\"},{\\\"settings\\\":{\\\"foreground\\\":\\\"#81A1C1\\\"},\\\"scope\\\":\\\"source.properties punctuation.separator.key-value.ini\\\"},{\\\"settings\\\":{\\\"foreground\\\":\\\"#8FBCBB\\\"},\\\"scope\\\":[\\\"text.html.markdown markup.fenced_code.block\\\",\\\"text.html.markdown markup.fenced_code.block punctuation.definition\\\"]},{\\\"settings\\\":{\\\"foreground\\\":\\\"#88C0D0\\\"},\\\"scope\\\":\\\"markup.heading\\\"},{\\\"settings\\\":{\\\"foreground\\\":\\\"#8FBCBB\\\"},\\\"scope\\\":[\\\"text.html.markdown markup.inline.raw\\\",\\\"text.html.markdown markup.inline.raw punctuation.definition.raw\\\"]},{\\\"settings\\\":{\\\"fontStyle\\\":\\\"italic\\\"},\\\"scope\\\":\\\"text.html.markdown markup.italic\\\"},{\\\"settings\\\":{\\\"fontStyle\\\":\\\"underline\\\"},\\\"scope\\\":\\\"text.html.markdown markup.underline.link\\\"},{\\\"settings\\\":{\\\"foreground\\\":\\\"#81A1C1\\\"},\\\"scope\\\":\\\"text.html.markdown beginning.punctuation.definition.list\\\"},{\\\"settings\\\":{\\\"foreground\\\":\\\"#8FBCBB\\\"},\\\"scope\\\":\\\"text.html.markdown beginning.punctuation.definition.quote\\\"},{\\\"settings\\\":{\\\"foreground\\\":\\\"#616E88\\\"},\\\"scope\\\":\\\"text.html.markdown markup.quote\\\"},{\\\"settings\\\":{\\\"foreground\\\":\\\"#81A1C1\\\"},\\\"scope\\\":\\\"text.html.markdown constant.character.math.tex\\\"},{\\\"settings\\\":{\\\"foreground\\\":\\\"#5E81AC\\\"},\\\"scope\\\":[\\\"text.html.markdown punctuation.definition.math.begin\\\",\\\"text.html.markdown punctuation.definition.math.end\\\"]},{\\\"settings\\\":{\\\"foreground\\\":\\\"#88C0D0\\\"},\\\"scope\\\":\\\"text.html.markdown punctuation.definition.function.math.tex\\\"},{\\\"settings\\\":{\\\"foreground\\\":\\\"#81A1C1\\\"},\\\"scope\\\":\\\"text.html.markdown punctuation.math.operator.latex\\\"},{\\\"settings\\\":{\\\"foreground\\\":\\\"#81A1C1\\\"},\\\"scope\\\":\\\"text.html.markdown punctuation.definition.heading\\\"},{\\\"settings\\\":{\\\"foreground\\\":\\\"#81A1C1\\\"},\\\"scope\\\":[\\\"text.html.markdown punctuation.definition.constant\\\",\\\"text.html.markdown punctuation.definition.string\\\"]},{\\\"settings\\\":{\\\"foreground\\\":\\\"#88C0D0\\\"},\\\"scope\\\":[\\\"text.html.markdown constant.other.reference.link\\\",\\\"text.html.markdown string.other.link.description\\\",\\\"text.html.markdown string.other.link.title\\\"]},{\\\"settings\\\":{\\\"foreground\\\":\\\"#D8DEE9\\\"},\\\"scope\\\":\\\"source.perl punctuation.definition.variable\\\"},{\\\"settings\\\":{\\\"foreground\\\":\\\"#88C0D0\\\"},\\\"scope\\\":[\\\"source.php meta.function-call\\\",\\\"source.php meta.function-call.object\\\"]},{\\\"settings\\\":{\\\"foreground\\\":\\\"#D08770\\\"},\\\"scope\\\":[\\\"source.python entity.name.function.decorator\\\",\\\"source.python meta.function.decorator support.type\\\"]},{\\\"settings\\\":{\\\"foreground\\\":\\\"#88C0D0\\\"},\\\"scope\\\":\\\"source.python meta.function-call.generic\\\"},{\\\"settings\\\":{\\\"foreground\\\":\\\"#88C0D0\\\"},\\\"scope\\\":\\\"source.python support.type\\\"},{\\\"settings\\\":{\\\"foreground\\\":\\\"#D8DEE9\\\"},\\\"scope\\\":[\\\"source.python variable.parameter.function.language\\\"]},{\\\"settings\\\":{\\\"foreground\\\":\\\"#81A1C1\\\"},\\\"scope\\\":[\\\"source.python meta.function.parameters variable.parameter.function.language.special.self\\\"]},{\\\"settings\\\":{\\\"foreground\\\":\\\"#81A1C1\\\"},\\\"scope\\\":[\\\"source.css.scss punctuation.definition.interpolation.begin.bracket.curly\\\",\\\"source.css.scss punctuation.definition.interpolation.end.bracket.curly\\\"]},{\\\"settings\\\":{\\\"foreground\\\":\\\"#D8DEE9\\\",\\\"fontStyle\\\":\\\"italic\\\"},\\\"scope\\\":\\\"source.css.scss variable.interpolation\\\"},{\\\"settings\\\":{\\\"foreground\\\":\\\"#D08770\\\"},\\\"scope\\\":[\\\"source.ts punctuation.decorator\\\",\\\"source.ts meta.decorator variable.other.readwrite\\\",\\\"source.ts meta.decorator entity.name.function\\\",\\\"source.tsx punctuation.decorator\\\",\\\"source.tsx meta.decorator variable.other.readwrite\\\",\\\"source.tsx meta.decorator entity.name.function\\\"]},{\\\"settings\\\":{\\\"foreground\\\":\\\"#D8DEE9\\\"},\\\"scope\\\":[\\\"source.ts meta.object-literal.key\\\",\\\"source.tsx meta.object-literal.key\\\"]},{\\\"settings\\\":{\\\"foreground\\\":\\\"#88C0D0\\\"},\\\"scope\\\":[\\\"source.ts meta.object-literal.key entity.name.function\\\",\\\"source.tsx meta.object-literal.key entity.name.function\\\"]},{\\\"settings\\\":{\\\"foreground\\\":\\\"#8FBCBB\\\"},\\\"scope\\\":[\\\"source.ts support.class\\\",\\\"source.ts support.type\\\",\\\"source.ts entity.name.type\\\",\\\"source.ts entity.name.class\\\",\\\"source.tsx support.class\\\",\\\"source.tsx support.type\\\",\\\"source.tsx entity.name.type\\\",\\\"source.tsx entity.name.class\\\"]},{\\\"settings\\\":{\\\"foreground\\\":\\\"#8FBCBB\\\"},\\\"scope\\\":[\\\"source.ts support.constant.math\\\",\\\"source.ts support.constant.dom\\\",\\\"source.ts support.constant.json\\\",\\\"source.tsx support.constant.math\\\",\\\"source.tsx support.constant.dom\\\",\\\"source.tsx support.constant.json\\\"]},{\\\"settings\\\":{\\\"foreground\\\":\\\"#D8DEE9\\\"},\\\"scope\\\":[\\\"source.ts support.variable\\\",\\\"source.tsx support.variable\\\"]},{\\\"settings\\\":{\\\"foreground\\\":\\\"#ECEFF4\\\"},\\\"scope\\\":[\\\"source.ts meta.embedded.line meta.brace.square\\\",\\\"source.ts meta.embedded.line meta.brace.round\\\",\\\"source.tsx meta.embedded.line meta.brace.square\\\",\\\"source.tsx meta.embedded.line meta.brace.round\\\"]},{\\\"settings\\\":{\\\"foreground\\\":\\\"#8FBCBB\\\"},\\\"scope\\\":\\\"text.xml entity.name.tag.namespace\\\"},{\\\"settings\\\":{\\\"foreground\\\":\\\"#5E81AC\\\"},\\\"scope\\\":\\\"text.xml keyword.other.doctype\\\"},{\\\"settings\\\":{\\\"foreground\\\":\\\"#5E81AC\\\"},\\\"scope\\\":\\\"text.xml meta.tag.preprocessor entity.name.tag\\\"},{\\\"settings\\\":{\\\"foreground\\\":\\\"#D08770\\\",\\\"fontStyle\\\":\\\"italic\\\"},\\\"scope\\\":[\\\"text.xml string.unquoted.cdata\\\",\\\"text.xml string.unquoted.cdata punctuation.definition.string\\\"]},{\\\"settings\\\":{\\\"foreground\\\":\\\"#8FBCBB\\\"},\\\"scope\\\":\\\"source.yaml entity.name.tag\\\"}],\\\"semanticTokenRules\\\":[],\\\"extensionData\\\":{\\\"_extensionId\\\":\\\"arcticicestudio.nord-visual-studio-code\\\",\\\"_extensionIsBuiltin\\\":false,\\\"_extensionName\\\":\\\"nord-visual-studio-code\\\",\\\"_extensionPublisher\\\":\\\"arcticicestudio\\\"},\\\"themeSemanticHighlighting\\\":true,\\\"colorMap\\\":{\\\"focusBorder\\\":\\\"#3b4252\\\",\\\"foreground\\\":\\\"#d8dee9\\\",\\\"activityBar.background\\\":\\\"#2e3440\\\",\\\"activityBar.dropBackground\\\":\\\"#3b4252\\\",\\\"activityBar.foreground\\\":\\\"#d8dee9\\\",\\\"activityBar.activeBorder\\\":\\\"#88c0d0\\\",\\\"activityBar.activeBackground\\\":\\\"#3b4252\\\",\\\"activityBarBadge.background\\\":\\\"#88c0d0\\\",\\\"activityBarBadge.foreground\\\":\\\"#2e3440\\\",\\\"badge.foreground\\\":\\\"#2e3440\\\",\\\"badge.background\\\":\\\"#88c0d0\\\",\\\"button.background\\\":\\\"#88c0d0ee\\\",\\\"button.foreground\\\":\\\"#2e3440\\\",\\\"button.hoverBackground\\\":\\\"#88c0d0\\\",\\\"button.secondaryBackground\\\":\\\"#434c5e\\\",\\\"button.secondaryForeground\\\":\\\"#d8dee9\\\",\\\"button.secondaryHoverBackground\\\":\\\"#4c566a\\\",\\\"charts.red\\\":\\\"#bf616a\\\",\\\"charts.blue\\\":\\\"#81a1c1\\\",\\\"charts.yellow\\\":\\\"#ebcb8b\\\",\\\"charts.orange\\\":\\\"#d08770\\\",\\\"charts.green\\\":\\\"#a3be8c\\\",\\\"charts.purple\\\":\\\"#b48ead\\\",\\\"charts.foreground\\\":\\\"#d8dee9\\\",\\\"charts.lines\\\":\\\"#88c0d0\\\",\\\"debugConsole.infoForeground\\\":\\\"#88c0d0\\\",\\\"debugConsole.warningForeground\\\":\\\"#ebcb8b\\\",\\\"debugConsole.errorForeground\\\":\\\"#bf616a\\\",\\\"debugConsole.sourceForeground\\\":\\\"#616e88\\\",\\\"debugConsoleInputIcon.foreground\\\":\\\"#81a1c1\\\",\\\"debugExceptionWidget.background\\\":\\\"#4c566a\\\",\\\"debugExceptionWidget.border\\\":\\\"#2e3440\\\",\\\"debugToolBar.background\\\":\\\"#3b4252\\\",\\\"descriptionForeground\\\":\\\"#d8dee9e6\\\",\\\"diffEditor.insertedTextBackground\\\":\\\"#81a1c133\\\",\\\"diffEditor.removedTextBackground\\\":\\\"#bf616a4d\\\",\\\"dropdown.background\\\":\\\"#3b4252\\\",\\\"dropdown.border\\\":\\\"#3b4252\\\",\\\"dropdown.foreground\\\":\\\"#d8dee9\\\",\\\"editorActiveLineNumber.foreground\\\":\\\"#d8dee9cc\\\",\\\"editorCursor.foreground\\\":\\\"#d8dee9\\\",\\\"editorHint.border\\\":\\\"#ebcb8b00\\\",\\\"editorHint.foreground\\\":\\\"#ebcb8b\\\",\\\"editorIndentGuide.background\\\":\\\"#434c5eb3\\\",\\\"editorIndentGuide.activeBackground\\\":\\\"#4c566a\\\",\\\"editorInlayHint.background\\\":\\\"#434c5e\\\",\\\"editorInlayHint.foreground\\\":\\\"#d8dee9\\\",\\\"editorLineNumber.foreground\\\":\\\"#4c566a\\\",\\\"editorLineNumber.activeForeground\\\":\\\"#d8dee9\\\",\\\"editorWhitespace.foreground\\\":\\\"#4c566ab3\\\",\\\"editorWidget.background\\\":\\\"#2e3440\\\",\\\"editorWidget.border\\\":\\\"#3b4252\\\",\\\"editor.background\\\":\\\"#2e3440\\\",\\\"editor.foreground\\\":\\\"#d8dee9\\\",\\\"editor.hoverHighlightBackground\\\":\\\"#3b4252\\\",\\\"editor.findMatchBackground\\\":\\\"#88c0d066\\\",\\\"editor.findMatchHighlightBackground\\\":\\\"#88c0d033\\\",\\\"editor.findRangeHighlightBackground\\\":\\\"#88c0d033\\\",\\\"editor.lineHighlightBackground\\\":\\\"#3b4252\\\",\\\"editor.lineHighlightBorder\\\":\\\"#3b4252\\\",\\\"editor.inactiveSelectionBackground\\\":\\\"#434c5ecc\\\",\\\"editor.inlineValuesBackground\\\":\\\"#4c566a\\\",\\\"editor.inlineValuesForeground\\\":\\\"#eceff4\\\",\\\"editor.selectionBackground\\\":\\\"#434c5ecc\\\",\\\"editor.selectionHighlightBackground\\\":\\\"#434c5ecc\\\",\\\"editor.rangeHighlightBackground\\\":\\\"#434c5e52\\\",\\\"editor.wordHighlightBackground\\\":\\\"#81a1c166\\\",\\\"editor.wordHighlightStrongBackground\\\":\\\"#81a1c199\\\",\\\"editor.stackFrameHighlightBackground\\\":\\\"#5e81ac\\\",\\\"editor.focusedStackFrameHighlightBackground\\\":\\\"#5e81ac\\\",\\\"editorError.foreground\\\":\\\"#bf616a\\\",\\\"editorError.border\\\":\\\"#bf616a00\\\",\\\"editorWarning.foreground\\\":\\\"#ebcb8b\\\",\\\"editorWarning.border\\\":\\\"#ebcb8b00\\\",\\\"editorBracketMatch.background\\\":\\\"#2e344000\\\",\\\"editorBracketMatch.border\\\":\\\"#88c0d0\\\",\\\"editorBracketHighlight.foreground1\\\":\\\"#8fbcbb\\\",\\\"editorBracketHighlight.foreground2\\\":\\\"#88c0d0\\\",\\\"editorBracketHighlight.foreground3\\\":\\\"#81a1c1\\\",\\\"editorBracketHighlight.foreground4\\\":\\\"#5e81ac\\\",\\\"editorBracketHighlight.foreground5\\\":\\\"#8fbcbb\\\",\\\"editorBracketHighlight.foreground6\\\":\\\"#88c0d0\\\",\\\"editorBracketHighlight.unexpectedBracket.foreground\\\":\\\"#bf616a\\\",\\\"editorCodeLens.foreground\\\":\\\"#4c566a\\\",\\\"editorGroup.background\\\":\\\"#2e3440\\\",\\\"editorGroup.border\\\":\\\"#3b425201\\\",\\\"editorGroup.dropBackground\\\":\\\"#3b425299\\\",\\\"editorGroupHeader.border\\\":\\\"#3b425200\\\",\\\"editorGroupHeader.noTabsBackground\\\":\\\"#2e3440\\\",\\\"editorGroupHeader.tabsBackground\\\":\\\"#2e3440\\\",\\\"editorGroupHeader.tabsBorder\\\":\\\"#3b425200\\\",\\\"editorGutter.background\\\":\\\"#2e3440\\\",\\\"editorGutter.modifiedBackground\\\":\\\"#ebcb8b\\\",\\\"editorGutter.addedBackground\\\":\\\"#a3be8c\\\",\\\"editorGutter.deletedBackground\\\":\\\"#bf616a\\\",\\\"editorHoverWidget.background\\\":\\\"#3b4252\\\",\\\"editorHoverWidget.border\\\":\\\"#3b4252\\\",\\\"editorLink.activeForeground\\\":\\\"#88c0d0\\\",\\\"editorMarkerNavigation.background\\\":\\\"#5e81acc0\\\",\\\"editorMarkerNavigationError.background\\\":\\\"#bf616ac0\\\",\\\"editorMarkerNavigationWarning.background\\\":\\\"#ebcb8bc0\\\",\\\"editorOverviewRuler.border\\\":\\\"#3b4252\\\",\\\"editorOverviewRuler.currentContentForeground\\\":\\\"#3b4252\\\",\\\"editorOverviewRuler.incomingContentForeground\\\":\\\"#3b4252\\\",\\\"editorOverviewRuler.findMatchForeground\\\":\\\"#88c0d066\\\",\\\"editorOverviewRuler.rangeHighlightForeground\\\":\\\"#88c0d066\\\",\\\"editorOverviewRuler.selectionHighlightForeground\\\":\\\"#88c0d066\\\",\\\"editorOverviewRuler.wordHighlightForeground\\\":\\\"#88c0d066\\\",\\\"editorOverviewRuler.wordHighlightStrongForeground\\\":\\\"#88c0d066\\\",\\\"editorOverviewRuler.modifiedForeground\\\":\\\"#ebcb8b\\\",\\\"editorOverviewRuler.addedForeground\\\":\\\"#a3be8c\\\",\\\"editorOverviewRuler.deletedForeground\\\":\\\"#bf616a\\\",\\\"editorOverviewRuler.errorForeground\\\":\\\"#bf616a\\\",\\\"editorOverviewRuler.warningForeground\\\":\\\"#ebcb8b\\\",\\\"editorOverviewRuler.infoForeground\\\":\\\"#81a1c1\\\",\\\"editorRuler.foreground\\\":\\\"#434c5e\\\",\\\"editorSuggestWidget.background\\\":\\\"#2e3440\\\",\\\"editorSuggestWidget.border\\\":\\\"#3b4252\\\",\\\"editorSuggestWidget.foreground\\\":\\\"#d8dee9\\\",\\\"editorSuggestWidget.focusHighlightForeground\\\":\\\"#88c0d0\\\",\\\"editorSuggestWidget.highlightForeground\\\":\\\"#88c0d0\\\",\\\"editorSuggestWidget.selectedBackground\\\":\\\"#434c5e\\\",\\\"editorSuggestWidget.selectedForeground\\\":\\\"#d8dee9\\\",\\\"extensionButton.prominentForeground\\\":\\\"#d8dee9\\\",\\\"extensionButton.prominentBackground\\\":\\\"#434c5e\\\",\\\"extensionButton.prominentHoverBackground\\\":\\\"#4c566a\\\",\\\"errorForeground\\\":\\\"#bf616a\\\",\\\"gitDecoration.modifiedResourceForeground\\\":\\\"#ebcb8b\\\",\\\"gitDecoration.deletedResourceForeground\\\":\\\"#bf616a\\\",\\\"gitDecoration.untrackedResourceForeground\\\":\\\"#a3be8c\\\",\\\"gitDecoration.ignoredResourceForeground\\\":\\\"#d8dee966\\\",\\\"gitDecoration.conflictingResourceForeground\\\":\\\"#5e81ac\\\",\\\"gitDecoration.submoduleResourceForeground\\\":\\\"#8fbcbb\\\",\\\"gitDecoration.stageDeletedResourceForeground\\\":\\\"#bf616a\\\",\\\"gitDecoration.stageModifiedResourceForeground\\\":\\\"#ebcb8b\\\",\\\"input.background\\\":\\\"#3b4252\\\",\\\"input.foreground\\\":\\\"#d8dee9\\\",\\\"input.placeholderForeground\\\":\\\"#d8dee999\\\",\\\"input.border\\\":\\\"#3b4252\\\",\\\"inputOption.activeBackground\\\":\\\"#5e81ac\\\",\\\"inputOption.activeBorder\\\":\\\"#5e81ac\\\",\\\"inputOption.activeForeground\\\":\\\"#eceff4\\\",\\\"inputValidation.errorBackground\\\":\\\"#bf616a\\\",\\\"inputValidation.errorBorder\\\":\\\"#bf616a\\\",\\\"inputValidation.infoBackground\\\":\\\"#81a1c1\\\",\\\"inputValidation.infoBorder\\\":\\\"#81a1c1\\\",\\\"inputValidation.warningBackground\\\":\\\"#d08770\\\",\\\"inputValidation.warningBorder\\\":\\\"#d08770\\\",\\\"keybindingLabel.background\\\":\\\"#4c566a\\\",\\\"keybindingLabel.border\\\":\\\"#4c566a\\\",\\\"keybindingLabel.bottomBorder\\\":\\\"#4c566a\\\",\\\"keybindingLabel.foreground\\\":\\\"#d8dee9\\\",\\\"list.activeSelectionBackground\\\":\\\"#88c0d0\\\",\\\"list.activeSelectionForeground\\\":\\\"#2e3440\\\",\\\"list.inactiveSelectionBackground\\\":\\\"#434c5e\\\",\\\"list.inactiveSelectionForeground\\\":\\\"#d8dee9\\\",\\\"list.inactiveFocusBackground\\\":\\\"#434c5ecc\\\",\\\"list.hoverForeground\\\":\\\"#eceff4\\\",\\\"list.focusForeground\\\":\\\"#d8dee9\\\",\\\"list.focusBackground\\\":\\\"#88c0d099\\\",\\\"list.focusHighlightForeground\\\":\\\"#eceff4\\\",\\\"list.hoverBackground\\\":\\\"#3b4252\\\",\\\"list.dropBackground\\\":\\\"#88c0d099\\\",\\\"list.highlightForeground\\\":\\\"#88c0d0\\\",\\\"list.errorForeground\\\":\\\"#bf616a\\\",\\\"list.warningForeground\\\":\\\"#ebcb8b\\\",\\\"merge.currentHeaderBackground\\\":\\\"#81a1c166\\\",\\\"merge.currentContentBackground\\\":\\\"#81a1c14d\\\",\\\"merge.incomingHeaderBackground\\\":\\\"#8fbcbb66\\\",\\\"merge.incomingContentBackground\\\":\\\"#8fbcbb4d\\\",\\\"merge.border\\\":\\\"#3b425200\\\",\\\"minimap.background\\\":\\\"#2e3440\\\",\\\"minimap.errorHighlight\\\":\\\"#bf616acc\\\",\\\"minimap.findMatchHighlight\\\":\\\"#88c0d0\\\",\\\"minimap.selectionHighlight\\\":\\\"#88c0d0cc\\\",\\\"minimap.warningHighlight\\\":\\\"#ebcb8bcc\\\",\\\"minimapGutter.addedBackground\\\":\\\"#a3be8c\\\",\\\"minimapGutter.deletedBackground\\\":\\\"#bf616a\\\",\\\"minimapGutter.modifiedBackground\\\":\\\"#ebcb8b\\\",\\\"minimapSlider.activeBackground\\\":\\\"#434c5eaa\\\",\\\"minimapSlider.background\\\":\\\"#434c5e99\\\",\\\"minimapSlider.hoverBackground\\\":\\\"#434c5eaa\\\",\\\"notification.background\\\":\\\"#3b4252\\\",\\\"notification.buttonBackground\\\":\\\"#434c5e\\\",\\\"notification.buttonForeground\\\":\\\"#d8dee9\\\",\\\"notification.buttonHoverBackground\\\":\\\"#4c566a\\\",\\\"notification.errorBackground\\\":\\\"#bf616a\\\",\\\"notification.errorForeground\\\":\\\"#2e3440\\\",\\\"notification.foreground\\\":\\\"#d8dee9\\\",\\\"notification.infoBackground\\\":\\\"#88c0d0\\\",\\\"notification.infoForeground\\\":\\\"#2e3440\\\",\\\"notification.warningBackground\\\":\\\"#ebcb8b\\\",\\\"notification.warningForeground\\\":\\\"#2e3440\\\",\\\"notificationCenter.border\\\":\\\"#3b425200\\\",\\\"notificationCenterHeader.background\\\":\\\"#2e3440\\\",\\\"notificationCenterHeader.foreground\\\":\\\"#88c0d0\\\",\\\"notificationLink.foreground\\\":\\\"#88c0d0\\\",\\\"notifications.background\\\":\\\"#3b4252\\\",\\\"notifications.border\\\":\\\"#2e3440\\\",\\\"notifications.foreground\\\":\\\"#d8dee9\\\",\\\"notificationToast.border\\\":\\\"#3b425200\\\",\\\"panel.background\\\":\\\"#2e3440\\\",\\\"panel.border\\\":\\\"#3b4252\\\",\\\"panelTitle.activeBorder\\\":\\\"#88c0d000\\\",\\\"panelTitle.activeForeground\\\":\\\"#88c0d0\\\",\\\"panelTitle.inactiveForeground\\\":\\\"#d8dee9\\\",\\\"peekView.border\\\":\\\"#4c566a\\\",\\\"peekViewEditor.background\\\":\\\"#2e3440\\\",\\\"peekViewEditorGutter.background\\\":\\\"#2e3440\\\",\\\"peekViewEditor.matchHighlightBackground\\\":\\\"#88c0d04d\\\",\\\"peekViewResult.background\\\":\\\"#2e3440\\\",\\\"peekViewResult.fileForeground\\\":\\\"#88c0d0\\\",\\\"peekViewResult.lineForeground\\\":\\\"#d8dee966\\\",\\\"peekViewResult.matchHighlightBackground\\\":\\\"#88c0d0cc\\\",\\\"peekViewResult.selectionBackground\\\":\\\"#434c5e\\\",\\\"peekViewResult.selectionForeground\\\":\\\"#d8dee9\\\",\\\"peekViewTitle.background\\\":\\\"#3b4252\\\",\\\"peekViewTitleDescription.foreground\\\":\\\"#d8dee9\\\",\\\"peekViewTitleLabel.foreground\\\":\\\"#88c0d0\\\",\\\"pickerGroup.border\\\":\\\"#3b4252\\\",\\\"pickerGroup.foreground\\\":\\\"#88c0d0\\\",\\\"progressBar.background\\\":\\\"#88c0d0\\\",\\\"quickInputList.focusBackground\\\":\\\"#88c0d0\\\",\\\"quickInputList.focusForeground\\\":\\\"#2e3440\\\",\\\"sash.hoverBorder\\\":\\\"#88c0d0\\\",\\\"scrollbar.shadow\\\":\\\"#00000066\\\",\\\"scrollbarSlider.activeBackground\\\":\\\"#434c5eaa\\\",\\\"scrollbarSlider.background\\\":\\\"#434c5e99\\\",\\\"scrollbarSlider.hoverBackground\\\":\\\"#434c5eaa\\\",\\\"selection.background\\\":\\\"#88c0d099\\\",\\\"sideBar.background\\\":\\\"#2e3440\\\",\\\"sideBar.foreground\\\":\\\"#d8dee9\\\",\\\"sideBar.border\\\":\\\"#3b4252\\\",\\\"sideBarSectionHeader.background\\\":\\\"#3b4252\\\",\\\"sideBarSectionHeader.foreground\\\":\\\"#d8dee9\\\",\\\"sideBarTitle.foreground\\\":\\\"#d8dee9\\\",\\\"statusBar.background\\\":\\\"#3b4252\\\",\\\"statusBar.debuggingBackground\\\":\\\"#5e81ac\\\",\\\"statusBar.debuggingForeground\\\":\\\"#d8dee9\\\",\\\"statusBar.noFolderForeground\\\":\\\"#d8dee9\\\",\\\"statusBar.noFolderBackground\\\":\\\"#3b4252\\\",\\\"statusBar.foreground\\\":\\\"#d8dee9\\\",\\\"statusBarItem.activeBackground\\\":\\\"#4c566a\\\",\\\"statusBarItem.hoverBackground\\\":\\\"#434c5e\\\",\\\"statusBarItem.prominentBackground\\\":\\\"#3b4252\\\",\\\"statusBarItem.prominentHoverBackground\\\":\\\"#434c5e\\\",\\\"statusBarItem.errorBackground\\\":\\\"#3b4252\\\",\\\"statusBarItem.errorForeground\\\":\\\"#bf616a\\\",\\\"statusBarItem.warningBackground\\\":\\\"#ebcb8b\\\",\\\"statusBarItem.warningForeground\\\":\\\"#2e3440\\\",\\\"statusBar.border\\\":\\\"#3b425200\\\",\\\"tab.activeBackground\\\":\\\"#3b4252\\\",\\\"tab.activeForeground\\\":\\\"#d8dee9\\\",\\\"tab.border\\\":\\\"#3b425200\\\",\\\"tab.activeBorder\\\":\\\"#88c0d000\\\",\\\"tab.unfocusedActiveBorder\\\":\\\"#88c0d000\\\",\\\"tab.inactiveBackground\\\":\\\"#2e3440\\\",\\\"tab.inactiveForeground\\\":\\\"#d8dee966\\\",\\\"tab.unfocusedActiveForeground\\\":\\\"#d8dee999\\\",\\\"tab.unfocusedInactiveForeground\\\":\\\"#d8dee966\\\",\\\"tab.hoverBackground\\\":\\\"#3b4252cc\\\",\\\"tab.unfocusedHoverBackground\\\":\\\"#3b4252b3\\\",\\\"tab.hoverBorder\\\":\\\"#88c0d000\\\",\\\"tab.unfocusedHoverBorder\\\":\\\"#88c0d000\\\",\\\"tab.activeBorderTop\\\":\\\"#88c0d000\\\",\\\"tab.unfocusedActiveBorderTop\\\":\\\"#88c0d000\\\",\\\"tab.lastPinnedBorder\\\":\\\"#4c566a\\\",\\\"terminal.background\\\":\\\"#2e3440\\\",\\\"terminal.foreground\\\":\\\"#d8dee9\\\",\\\"terminal.ansiBlack\\\":\\\"#3b4252\\\",\\\"terminal.ansiRed\\\":\\\"#bf616a\\\",\\\"terminal.ansiGreen\\\":\\\"#a3be8c\\\",\\\"terminal.ansiYellow\\\":\\\"#ebcb8b\\\",\\\"terminal.ansiBlue\\\":\\\"#81a1c1\\\",\\\"terminal.ansiMagenta\\\":\\\"#b48ead\\\",\\\"terminal.ansiCyan\\\":\\\"#88c0d0\\\",\\\"terminal.ansiWhite\\\":\\\"#e5e9f0\\\",\\\"terminal.ansiBrightBlack\\\":\\\"#4c566a\\\",\\\"terminal.ansiBrightRed\\\":\\\"#bf616a\\\",\\\"terminal.ansiBrightGreen\\\":\\\"#a3be8c\\\",\\\"terminal.ansiBrightYellow\\\":\\\"#ebcb8b\\\",\\\"terminal.ansiBrightBlue\\\":\\\"#81a1c1\\\",\\\"terminal.ansiBrightMagenta\\\":\\\"#b48ead\\\",\\\"terminal.ansiBrightCyan\\\":\\\"#8fbcbb\\\",\\\"terminal.ansiBrightWhite\\\":\\\"#eceff4\\\",\\\"terminal.tab.activeBorder\\\":\\\"#88c0d0\\\",\\\"textBlockQuote.background\\\":\\\"#3b4252\\\",\\\"textBlockQuote.border\\\":\\\"#81a1c1\\\",\\\"textCodeBlock.background\\\":\\\"#4c566a\\\",\\\"textLink.activeForeground\\\":\\\"#88c0d0\\\",\\\"textLink.foreground\\\":\\\"#88c0d0\\\",\\\"textPreformat.foreground\\\":\\\"#8fbcbb\\\",\\\"textSeparator.foreground\\\":\\\"#eceff4\\\",\\\"titleBar.activeBackground\\\":\\\"#2e3440\\\",\\\"titleBar.activeForeground\\\":\\\"#d8dee9\\\",\\\"titleBar.border\\\":\\\"#2e344000\\\",\\\"titleBar.inactiveBackground\\\":\\\"#2e3440\\\",\\\"titleBar.inactiveForeground\\\":\\\"#d8dee966\\\",\\\"tree.indentGuidesStroke\\\":\\\"#616e88\\\",\\\"walkThrough.embeddedEditorBackground\\\":\\\"#2e3440\\\",\\\"welcomePage.buttonBackground\\\":\\\"#434c5e\\\",\\\"welcomePage.buttonHoverBackground\\\":\\\"#4c566a\\\",\\\"widget.shadow\\\":\\\"#00000066\\\"},\\\"watch\\\":false}\"},\"commandPalette.mru.cache\":{\"version\":1,\"value\":\"{\\\"usesLRU\\\":true,\\\"entries\\\":[{\\\"key\\\":\\\"python.enableLinting\\\",\\\"value\\\":34},{\\\"key\\\":\\\"python.runLinting\\\",\\\"value\\\":36},{\\\"key\\\":\\\"autoDocstring.generateDocstring\\\",\\\"value\\\":70},{\\\"key\\\":\\\"python.sortImports\\\",\\\"value\\\":72},{\\\"key\\\":\\\"editor.action.formatDocument\\\",\\\"value\\\":73},{\\\"key\\\":\\\"editor.action.formatSelection\\\",\\\"value\\\":74},{\\\"key\\\":\\\"python.setLinter\\\",\\\"value\\\":76},{\\\"key\\\":\\\"editor.action.formatDocument.multiple\\\",\\\"value\\\":77},{\\\"key\\\":\\\"gitProjectManager.refreshProjects\\\",\\\"value\\\":80},{\\\"key\\\":\\\"gitProjectManager.openProject\\\",\\\"value\\\":82}]}\"},\"commandPalette.mru.counter\":{\"version\":1,\"value\":\"83\"},\"cpp.1.lastSessionDate\":{\"version\":1,\"value\":\"Mon Oct 09 2023\"},\"cpp.1.sessionCount\":{\"version\":1,\"value\":\"18\"},\"csharp.1.lastSessionDate\":{\"version\":1,\"value\":\"Mon Oct 09 2023\"},\"csharp.1.sessionCount\":{\"version\":1,\"value\":\"18\"},\"fileBasedRecommendations/promptedRecommendations\":{\"version\":1,\"value\":\"{\\\"yaml\\\":[\\\"github.vscode-github-actions\\\"]}\"},\"github-mstuttgart\":{\"version\":1,\"value\":\"[{\\\"id\\\":\\\"github.vscode-github-actions\\\",\\\"name\\\":\\\"GitHub Actions\\\",\\\"allowed\\\":true}]\"},\"http.linkProtectionTrustedDomains\":{\"version\":1,\"value\":\"[\\\"https://pylint.readthedocs.io\\\"]\"},\"java.2.lastSessionDate\":{\"version\":1,\"value\":\"Mon Oct 09 2023\"},\"java.2.sessionCount\":{\"version\":1,\"value\":\"18\"},\"javascript.1.lastSessionDate\":{\"version\":1,\"value\":\"Mon Oct 09 2023\"},\"javascript.1.sessionCount\":{\"version\":1,\"value\":\"18\"},\"memento/gettingStartedService\":{\"version\":1,\"value\":\"{\\\"pickColorTheme\\\":{\\\"done\\\":true},\\\"installGit\\\":{\\\"done\\\":true}}\"},\"memento/workbench.editor.keybindings\":{\"version\":1,\"value\":\"{\\\"searchHistory\\\":[\\\"esc\\\",\\\"simple\\\"]}\"},\"nps/isCandidate\":{\"version\":1,\"value\":\"false\"},\"nps/lastSessionDate\":{\"version\":1,\"value\":\"Wed Sep 27 2023\"},\"nps/sessionCount\":{\"version\":1,\"value\":\"9\"},\"nps/skipVersion\":{\"version\":1,\"value\":\"1.82.2\"},\"snippets.usageTimestamps\":{\"version\":1,\"value\":\"[[\\\"snippets/xml.json/odoo_ir_cron\\\",1696155428091],[\\\"snippets/python.json/odoo_field_selection\\\",1696190960465],[\\\"snippets/xml.json/odoo_xpath\\\",1696256357064],[\\\"snippets/xml.json/odoo_field\\\",1696275751820],[\\\"snippets/xml.json/odoo_group\\\",1696357647722],[\\\"snippets/python.json/ipdb_python_debugger\\\",1696859758141]]\"},\"terminal.hidden\":{\"version\":1,\"value\":\"[{\\\"id\\\":\\\"terminal\\\",\\\"isHidden\\\":false}]\"},\"terminal.integrated.showTerminalConfigPrompt\":{\"version\":1,\"value\":\"false\"},\"themeUpdatedNotificationShown\":{\"version\":1,\"value\":\"true\"},\"typescript.1.editedCount\":{\"version\":1,\"value\":\"1\"},\"typescript.1.editedDate\":{\"version\":1,\"value\":\"Sun Oct 01 2023\"},\"typescript.1.lastSessionDate\":{\"version\":1,\"value\":\"Mon Oct 09 2023\"},\"typescript.1.sessionCount\":{\"version\":1,\"value\":\"18\"},\"workbench.activity.pinnedViewlets2\":{\"version\":1,\"value\":\"[{\\\"id\\\":\\\"workbench.view.explorer\\\",\\\"pinned\\\":true,\\\"visible\\\":true,\\\"order\\\":0},{\\\"id\\\":\\\"workbench.view.search\\\",\\\"pinned\\\":true,\\\"visible\\\":true,\\\"order\\\":1},{\\\"id\\\":\\\"workbench.view.scm\\\",\\\"pinned\\\":true,\\\"visible\\\":true,\\\"order\\\":2},{\\\"id\\\":\\\"workbench.view.debug\\\",\\\"pinned\\\":true,\\\"visible\\\":true,\\\"order\\\":3},{\\\"id\\\":\\\"workbench.view.extensions\\\",\\\"pinned\\\":true,\\\"visible\\\":true,\\\"order\\\":4},{\\\"id\\\":\\\"workbench.view.extension.bookmarks\\\",\\\"pinned\\\":true,\\\"visible\\\":true,\\\"order\\\":8},{\\\"id\\\":\\\"workbench.view.remote\\\",\\\"pinned\\\":true,\\\"visible\\\":true,\\\"order\\\":4},{\\\"id\\\":\\\"workbench.view.extension.test\\\",\\\"pinned\\\":true,\\\"visible\\\":true,\\\"order\\\":6},{\\\"id\\\":\\\"workbench.view.extension.references-view\\\",\\\"pinned\\\":true,\\\"visible\\\":false,\\\"order\\\":7},{\\\"id\\\":\\\"workbench.view.extension.vscode-notes\\\",\\\"pinned\\\":true,\\\"visible\\\":true,\\\"order\\\":9},{\\\"id\\\":\\\"workbench.view.extension.gitlens\\\",\\\"pinned\\\":true,\\\"visible\\\":true,\\\"order\\\":10},{\\\"id\\\":\\\"workbench.view.extension.gitlensInspect\\\",\\\"pinned\\\":true,\\\"visible\\\":true,\\\"order\\\":11},{\\\"id\\\":\\\"workbench.view.extension.kubernetesView\\\",\\\"pinned\\\":true,\\\"visible\\\":true,\\\"order\\\":12},{\\\"id\\\":\\\"workbench.view.extension.github-actions\\\",\\\"pinned\\\":true,\\\"visible\\\":false,\\\"order\\\":12},{\\\"id\\\":\\\"workbench.view.extension.dockerView\\\",\\\"pinned\\\":true,\\\"visible\\\":true,\\\"order\\\":13},{\\\"id\\\":\\\"workbench.view.extension.ansible-lightspeed-explorer\\\",\\\"pinned\\\":true,\\\"visible\\\":false,\\\"order\\\":13},{\\\"id\\\":\\\"workbench.panel.chatSidebar\\\",\\\"pinned\\\":true,\\\"visible\\\":false,\\\"order\\\":100},{\\\"id\\\":\\\"userDataProfiles\\\",\\\"pinned\\\":true,\\\"visible\\\":false},{\\\"id\\\":\\\"workbench.view.sync\\\",\\\"pinned\\\":true,\\\"visible\\\":false},{\\\"id\\\":\\\"workbench.view.editSessions\\\",\\\"pinned\\\":true,\\\"visible\\\":false}]\"},\"workbench.explorer.views.state.hidden\":{\"version\":1,\"value\":\"[{\\\"id\\\":\\\"outline\\\",\\\"isHidden\\\":false},{\\\"id\\\":\\\"timeline\\\",\\\"isHidden\\\":false},{\\\"id\\\":\\\"workbench.explorer.openEditorsView\\\",\\\"isHidden\\\":true},{\\\"id\\\":\\\"workbench.explorer.emptyView\\\",\\\"isHidden\\\":false},{\\\"id\\\":\\\"npm\\\",\\\"isHidden\\\":true},{\\\"id\\\":\\\"xmlTreeView\\\",\\\"isHidden\\\":false},{\\\"id\\\":\\\"txtsyntaxHighlightExplore\\\",\\\"isHidden\\\":false},{\\\"id\\\":\\\"filters\\\",\\\"isHidden\\\":false},{\\\"id\\\":\\\"ansible.lightspeed.trainingMatchPanel\\\",\\\"isHidden\\\":false},{\\\"id\\\":\\\"lightspeed-explorer-treeview\\\",\\\"isHidden\\\":false},{\\\"id\\\":\\\"lightspeed-feedback-webview\\\",\\\"isHidden\\\":false},{\\\"id\\\":\\\"dockerContainers\\\",\\\"isHidden\\\":false},{\\\"id\\\":\\\"dockerImages\\\",\\\"isHidden\\\":false},{\\\"id\\\":\\\"dockerRegistries\\\",\\\"isHidden\\\":false},{\\\"id\\\":\\\"dockerNetworks\\\",\\\"isHidden\\\":false},{\\\"id\\\":\\\"dockerVolumes\\\",\\\"isHidden\\\":false},{\\\"id\\\":\\\"vscode-docker.views.dockerContexts\\\",\\\"isHidden\\\":false},{\\\"id\\\":\\\"vscode-docker.views.help\\\",\\\"isHidden\\\":false},{\\\"id\\\":\\\"workbench.explorer.fileView\\\",\\\"isHidden\\\":false}]\"},\"workbench.panel.alignment\":{\"version\":1,\"value\":\"center\"},\"workbench.panel.markers.hidden\":{\"version\":1,\"value\":\"[{\\\"id\\\":\\\"workbench.panel.markers.view\\\",\\\"isHidden\\\":false}]\"},\"workbench.panel.output.hidden\":{\"version\":1,\"value\":\"[{\\\"id\\\":\\\"workbench.panel.output\\\",\\\"isHidden\\\":false}]\"},\"workbench.panel.pinnedPanels\":{\"version\":1,\"value\":\"[{\\\"id\\\":\\\"workbench.panel.markers\\\",\\\"name\\\":\\\"Problems\\\",\\\"pinned\\\":true,\\\"order\\\":0,\\\"visible\\\":true},{\\\"id\\\":\\\"workbench.panel.output\\\",\\\"name\\\":\\\"Output\\\",\\\"pinned\\\":true,\\\"order\\\":1,\\\"visible\\\":true},{\\\"id\\\":\\\"workbench.panel.repl\\\",\\\"name\\\":\\\"Debug Console\\\",\\\"pinned\\\":true,\\\"order\\\":2,\\\"visible\\\":true},{\\\"id\\\":\\\"terminal\\\",\\\"name\\\":\\\"Terminal\\\",\\\"pinned\\\":true,\\\"order\\\":3,\\\"visible\\\":true},{\\\"id\\\":\\\"workbench.panel.testResults\\\",\\\"name\\\":\\\"Test Results\\\",\\\"pinned\\\":true,\\\"order\\\":3,\\\"visible\\\":false},{\\\"id\\\":\\\"~remote.forwardedPortsContainer\\\",\\\"name\\\":\\\"Ports\\\",\\\"pinned\\\":true,\\\"order\\\":5,\\\"visible\\\":true},{\\\"id\\\":\\\"workbench.view.extension.gitlensPanel\\\",\\\"name\\\":\\\"GitLens\\\",\\\"pinned\\\":true,\\\"order\\\":6,\\\"visible\\\":true},{\\\"id\\\":\\\"workbench.view.extension.lightspeed-training-match-panel\\\",\\\"name\\\":\\\"Ansible\\\",\\\"pinned\\\":true,\\\"order\\\":7,\\\"visible\\\":false},{\\\"id\\\":\\\"refactorPreview\\\",\\\"name\\\":\\\"Refactor Preview\\\",\\\"pinned\\\":true,\\\"visible\\\":false}]\"},\"workbench.panel.repl.hidden\":{\"version\":1,\"value\":\"[{\\\"id\\\":\\\"workbench.panel.repl.view\\\",\\\"isHidden\\\":false}]\"},\"workbench.scm.views.state.hidden\":{\"version\":1,\"value\":\"[{\\\"id\\\":\\\"workbench.scm.repositories\\\",\\\"isHidden\\\":true},{\\\"id\\\":\\\"workbench.scm\\\",\\\"isHidden\\\":false},{\\\"id\\\":\\\"gitlens.views.repositories\\\",\\\"isHidden\\\":true},{\\\"id\\\":\\\"gitlens.views.commits\\\",\\\"isHidden\\\":false},{\\\"id\\\":\\\"gitlens.views.branches\\\",\\\"isHidden\\\":false},{\\\"id\\\":\\\"gitlens.views.remotes\\\",\\\"isHidden\\\":false},{\\\"id\\\":\\\"gitlens.views.stashes\\\",\\\"isHidden\\\":false},{\\\"id\\\":\\\"gitlens.views.tags\\\",\\\"isHidden\\\":false},{\\\"id\\\":\\\"gitlens.views.worktrees\\\",\\\"isHidden\\\":false},{\\\"id\\\":\\\"gitlens.views.contributors\\\",\\\"isHidden\\\":false},{\\\"id\\\":\\\"workbench.scm.sync\\\",\\\"isHidden\\\":false}]\"},\"workbench.statusbar.hidden\":{\"version\":1,\"value\":\"[\\\"status.workspaceTrust.1695077708411\\\",\\\"status.workspaceTrust.9784a40be16a92c6e0a8c5790645a376\\\",\\\"status.workspaceTrust.83f02c7a60d1816241814d14a82cebc3\\\",\\\"status.workspaceTrust.693423aa321decf2e01a9c58cfbc3f29\\\",\\\"status.workspaceTrust.ae0811e3d6d33d5a44ff3c6a56464ef3\\\",\\\"status.workspaceTrust.6067b19161a1fc6d07fb32c24314010a\\\",\\\"status.workspaceTrust.1696162808166\\\",\\\"status.workspaceTrust.21761362d65478b0e177433d198da819\\\",\\\"status.workspaceTrust.1696249981791\\\",\\\"status.workspaceTrust.0281f8da3e0d80e7a6c2a541cff1da5e\\\",\\\"status.workspaceTrust.7a3b200e0fee96a6a7eea0c0dece2b00\\\"]\"},\"workbench.telemetryOptOutShown\":{\"version\":1,\"value\":\"true\"},\"workbench.view.debug.state.hidden\":{\"version\":1,\"value\":\"[{\\\"id\\\":\\\"workbench.debug.welcome\\\",\\\"isHidden\\\":false},{\\\"id\\\":\\\"workbench.debug.variablesView\\\",\\\"isHidden\\\":false},{\\\"id\\\":\\\"workbench.debug.watchExpressionsView\\\",\\\"isHidden\\\":false},{\\\"id\\\":\\\"workbench.debug.callStackView\\\",\\\"isHidden\\\":false},{\\\"id\\\":\\\"workbench.debug.loadedScriptsView\\\",\\\"isHidden\\\":false},{\\\"id\\\":\\\"workbench.debug.breakPointsView\\\",\\\"isHidden\\\":false},{\\\"id\\\":\\\"jsBrowserBreakpoints\\\",\\\"isHidden\\\":false},{\\\"id\\\":\\\"jsExcludedCallers\\\",\\\"isHidden\\\":false}]\"},\"workbench.view.extension.dockerView.state.hidden\":{\"version\":1,\"value\":\"[{\\\"id\\\":\\\"dockerContainers\\\",\\\"isHidden\\\":false},{\\\"id\\\":\\\"dockerImages\\\",\\\"isHidden\\\":false},{\\\"id\\\":\\\"dockerRegistries\\\",\\\"isHidden\\\":false},{\\\"id\\\":\\\"dockerNetworks\\\",\\\"isHidden\\\":false},{\\\"id\\\":\\\"dockerVolumes\\\",\\\"isHidden\\\":false},{\\\"id\\\":\\\"vscode-docker.views.dockerContexts\\\",\\\"isHidden\\\":false},{\\\"id\\\":\\\"vscode-docker.views.help\\\",\\\"isHidden\\\":false}]\"},\"workbench.view.extension.github-actions.state.hidden\":{\"version\":1,\"value\":\"[{\\\"id\\\":\\\"github-actions.current-branch\\\",\\\"isHidden\\\":false},{\\\"id\\\":\\\"github-actions.workflows\\\",\\\"isHidden\\\":false},{\\\"id\\\":\\\"github-actions.settings\\\",\\\"isHidden\\\":false},{\\\"id\\\":\\\"github-actions.empty-view\\\",\\\"isHidden\\\":false}]\"},\"workbench.view.extension.gitlensPanel.state.hidden\":{\"version\":1,\"value\":\"[{\\\"id\\\":\\\"gitlens.views.graph\\\",\\\"isHidden\\\":false},{\\\"id\\\":\\\"gitlens.views.graphDetails\\\",\\\"isHidden\\\":false}]\"},\"workbench.view.extension.test.state.hidden\":{\"version\":1,\"value\":\"[{\\\"id\\\":\\\"workbench.view.testing\\\",\\\"isHidden\\\":false}]\"},\"workbench.view.extensions.state.hidden\":{\"version\":1,\"value\":\"[{\\\"id\\\":\\\"workbench.views.extensions.installed\\\",\\\"isHidden\\\":false},{\\\"id\\\":\\\"workbench.views.extensions.searchOutdated\\\",\\\"isHidden\\\":false},{\\\"id\\\":\\\"workbench.views.extensions.workspaceRecommendations\\\",\\\"isHidden\\\":false},{\\\"id\\\":\\\"workbench.views.extensions.popular\\\",\\\"isHidden\\\":false},{\\\"id\\\":\\\"workbench.views.extensions.searchRecentlyUpdated\\\",\\\"isHidden\\\":false},{\\\"id\\\":\\\"workbench.views.extensions.otherRecommendations\\\",\\\"isHidden\\\":false},{\\\"id\\\":\\\"extensions.recommendedList\\\",\\\"isHidden\\\":false},{\\\"id\\\":\\\"workbench.views.extensions.enabled\\\",\\\"isHidden\\\":true},{\\\"id\\\":\\\"workbench.views.extensions.disabled\\\",\\\"isHidden\\\":true},{\\\"id\\\":\\\"workbench.views.extensions.marketplace\\\",\\\"isHidden\\\":false},{\\\"id\\\":\\\"workbench.views.extensions.searchInstalled\\\",\\\"isHidden\\\":false},{\\\"id\\\":\\\"workbench.views.extensions.searchEnabled\\\",\\\"isHidden\\\":false},{\\\"id\\\":\\\"workbench.views.extensions.searchDisabled\\\",\\\"isHidden\\\":false},{\\\"id\\\":\\\"workbench.views.extensions.searchBuiltin\\\",\\\"isHidden\\\":false},{\\\"id\\\":\\\"workbench.views.extensions.searchWorkspaceUnsupported\\\",\\\"isHidden\\\":false},{\\\"id\\\":\\\"workbench.views.extensions.builtinFeatureExtensions\\\",\\\"isHidden\\\":false},{\\\"id\\\":\\\"workbench.views.extensions.builtinThemeExtensions\\\",\\\"isHidden\\\":false},{\\\"id\\\":\\\"workbench.views.extensions.builtinProgrammingLanguageExtensions\\\",\\\"isHidden\\\":false},{\\\"id\\\":\\\"workbench.views.extensions.untrustedUnsupportedExtensions\\\",\\\"isHidden\\\":false},{\\\"id\\\":\\\"workbench.views.extensions.untrustedPartiallySupportedExtensions\\\",\\\"isHidden\\\":false},{\\\"id\\\":\\\"workbench.views.extensions.virtualUnsupportedExtensions\\\",\\\"isHidden\\\":false},{\\\"id\\\":\\\"workbench.views.extensions.virtualPartiallySupportedExtensions\\\",\\\"isHidden\\\":false},{\\\"id\\\":\\\"workbench.views.extensions.deprecatedExtensions\\\",\\\"isHidden\\\":false}]\"},\"workbench.view.remote.state.hidden\":{\"version\":1,\"value\":\"[{\\\"id\\\":\\\"targetsContainers\\\",\\\"isHidden\\\":false},{\\\"id\\\":\\\"detailsContainers\\\",\\\"isHidden\\\":false},{\\\"id\\\":\\\"devVolumes\\\",\\\"isHidden\\\":false}]\"},\"workbench.view.search.state.hidden\":{\"version\":1,\"value\":\"[{\\\"id\\\":\\\"workbench.view.search\\\",\\\"isHidden\\\":false}]\"},\"workbench.view.sync.state.hidden\":{\"version\":1,\"value\":\"[{\\\"id\\\":\\\"workbench.views.sync.conflicts\\\",\\\"isHidden\\\":false},{\\\"id\\\":\\\"workbench.views.sync.remoteActivity\\\",\\\"isHidden\\\":false},{\\\"id\\\":\\\"workbench.views.sync.machines\\\",\\\"isHidden\\\":false},{\\\"id\\\":\\\"workbench.views.sync.localActivity\\\",\\\"isHidden\\\":true},{\\\"id\\\":\\\"workbench.views.sync.troubleshoot\\\",\\\"isHidden\\\":true},{\\\"id\\\":\\\"workbench.views.sync.externalActivity\\\",\\\"isHidden\\\":false}]\"},\"workbench.welcomePage.walkthroughMetadata\":{\"version\":1,\"value\":\"[[\\\"alefragnani.Bookmarks#bookmarksWelcome\\\",{\\\"firstSeen\\\":1695077710261,\\\"stepIDs\\\":[\\\"toggle\\\",\\\"navigateToBookmarks\\\",\\\"defineLabelsForYourBookmarks\\\",\\\"exclusiveSideBar\\\",\\\"workingWithRemotes\\\",\\\"customizingAppearance\\\"],\\\"manaullyOpened\\\":false}],[\\\"eamodio.gitlens#gitlens.welcome\\\",{\\\"firstSeen\\\":1695077710262,\\\"stepIDs\\\":[\\\"gitlens.welcome.tutorial\\\",\\\"gitlens.welcome.sidebars\\\",\\\"gitlens.welcome.currentLineBlame\\\",\\\"gitlens.welcome.fileAnnotations\\\",\\\"gitlens.welcome.revisionHistory\\\",\\\"gitlens.welcome.commitGraph\\\",\\\"gitlens.welcome.workspaces\\\",\\\"gitlens.welcome.hostingServiceIntegrations\\\",\\\"gitlens.welcome.labs\\\",\\\"gitlens.welcome.preview\\\",\\\"gitlens.welcome.trial\\\",\\\"gitlens.welcome.services\\\",\\\"gitlens.welcome.additional\\\"],\\\"manaullyOpened\\\":false}],[\\\"ms-azuretools.vscode-docker#dockerStart\\\",{\\\"firstSeen\\\":1695077710262,\\\"stepIDs\\\":[\\\"openFolder\\\",\\\"openFolderMac\\\",\\\"scaffold\\\",\\\"buildImage\\\",\\\"runContainer\\\",\\\"dockerExplorer\\\",\\\"pushImage\\\",\\\"azDeploy\\\",\\\"learn\\\"],\\\"manaullyOpened\\\":false}],[\\\"ms-python.python#pythonWelcome\\\",{\\\"firstSeen\\\":1695077710262,\\\"stepIDs\\\":[\\\"python.createPythonFile\\\",\\\"python.installPythonWin8\\\",\\\"python.installPythonMac\\\",\\\"python.installPythonLinux\\\",\\\"python.selectInterpreter\\\",\\\"python.createEnvironment\\\",\\\"python.runAndDebug\\\",\\\"python.learnMoreWithDS\\\"],\\\"manaullyOpened\\\":false}],[\\\"ms-python.python#pythonWelcome2\\\",{\\\"firstSeen\\\":1695077710262,\\\"stepIDs\\\":[\\\"python.createPythonFolder\\\",\\\"python.createPythonFile\\\",\\\"python.installPythonWin8\\\",\\\"python.installPythonMac\\\",\\\"python.installPythonLinux\\\",\\\"python.createEnvironment2\\\",\\\"python.runAndDebug\\\",\\\"python.learnMoreWithDS2\\\"],\\\"manaullyOpened\\\":false}],[\\\"ms-python.python#pythonDataScienceWelcome\\\",{\\\"firstSeen\\\":1695077710262,\\\"stepIDs\\\":[\\\"python.installJupyterExt\\\",\\\"python.createNewNotebook\\\",\\\"python.openInteractiveWindow\\\",\\\"python.dataScienceLearnMore\\\"],\\\"manaullyOpened\\\":false}]]\"},\"~remote.forwardedPortsContainer.hidden\":{\"version\":1,\"value\":\"[{\\\"id\\\":\\\"~remote.forwardedPorts\\\",\\\"isHidden\\\":false}]\"}}}"}