{"version":1,"resource":"file:///home/michell/Workspace/multidadosti/odoo/multierp/src/l10n_br/br_nfe/models/invoice_electronic.py","entries":[{"id":"awjs.py","timestamp":1696857879323},{"id":"2N38.py","timestamp":1696858232335},{"id":"telK.py","timestamp":1696858247183},{"id":"iIXI.py","timestamp":1696858270327},{"id":"m4Vw.py","timestamp":1696858307272},{"id":"XsXs.py","timestamp":1696858415733},{"id":"RC3w.py","timestamp":1696858733298},{"id":"dBTF.py","timestamp":1696859551610},{"id":"UeN5.py","source":"undoRedo.source","timestamp":1696859564182},{"id":"vsTP.py","timestamp":1696859574898},{"id":"dt5M.py","timestamp":1696859600694},{"id":"L1b6.py","timestamp":1696859660250},{"id":"b72j.py","timestamp":1696859759150},{"id":"vFPH.py","timestamp":1696859909826},{"id":"ySOQ.py","timestamp":1696860084463},{"id":"v061.py","timestamp":1697738508530},{"id":"SE40.py","source":"Add '# type: ignore' to suppress warning","timestamp":1697743948543},{"id":"IrWj.py","timestamp":1697743952007},{"id":"K9ve.py","timestamp":1698848053417},{"id":"QPjQ.py","timestamp":1698848082785},{"id":"DswE.py","timestamp":1698848162926},{"id":"fYdZ.py","timestamp":1698851855643},{"id":"0Z8b.py","timestamp":1699622604795},{"id":"Cd3o.py","timestamp":1699622620459},{"id":"6vTD.py","timestamp":1699622705674},{"id":"yLf2.py","timestamp":1699622750922}]}